turbopelican/__init__.py
turbopelican/__main__.py
turbopelican/_args.py
turbopelican/py.typed
turbopelican/_commands/__init__.py
turbopelican/_commands/adorn/__init__.py
turbopelican/_commands/adorn/adorn.py
turbopelican/_commands/adorn/config.py
turbopelican/_commands/adorn/create.py
turbopelican/_commands/adorn/tests/__init__.py
turbopelican/_commands/adorn/tests/test_config.py
turbopelican/_commands/adorn/tests/test_create.py
turbopelican/_commands/init/__init__.py
turbopelican/_commands/init/config.py
turbopelican/_commands/init/create.py
turbopelican/_commands/init/init.py
turbopelican/_commands/init/tests/__init__.py
turbopelican/_commands/init/tests/test_config.py
turbopelican/_commands/init/tests/test_create.py
turbopelican/_templates/minimal/pelicanconf.py
turbopelican/_templates/minimal/pyproject.toml
turbopelican/_templates/newsite/.gitignore
turbopelican/_templates/newsite/.python-version
turbopelican/_templates/newsite/README.md
turbopelican/_templates/newsite/pelicanconf.py
turbopelican/_templates/newsite/pyproject.toml
turbopelican/_templates/newsite/turbopelican.toml
turbopelican/_templates/newsite/.github/workflows/turbopelican.yml
turbopelican/_templates/newsite/content/index.md
turbopelican/_templates/newsite/content/my-article.md
turbopelican/_templates/newsite/content/images/logo.svg
turbopelican/_templates/newsite/content/static/favicon.ico
turbopelican/_templates/newsite/themes/plain-theme/static/css/styles.css
turbopelican/_templates/newsite/themes/plain-theme/templates/archives.html
turbopelican/_templates/newsite/themes/plain-theme/templates/article.html
turbopelican/_templates/newsite/themes/plain-theme/templates/author.html
turbopelican/_templates/newsite/themes/plain-theme/templates/authors.html
turbopelican/_templates/newsite/themes/plain-theme/templates/base.html
turbopelican/_templates/newsite/themes/plain-theme/templates/categories.html
turbopelican/_templates/newsite/themes/plain-theme/templates/category.html
turbopelican-0.6.0.dist-info/METADATA
turbopelican-0.6.0.dist-info/WHEEL
turbopelican-0.6.0.dist-info/entry_points.txt
turbopelican-0.6.0.dist-info/licenses/LICENSE.txt
turbopelican-0.6.0.dist-info/RECORD
