Metadata-Version: 2.4
Name: turbopelican
Version: 0.6.0
Summary: An uber-quick tool to create a Pelican static-site and deploy it to GitHub Pages.
Project-URL: Source, https://github.com/turbopelican/turbopelican
Project-URL: Issues, https://github.com/turbopelican/turbopelican/issues
Project-URL: Changelog, https://github.com/turbopelican/turbopelican/blob/main/CHANGELOG.md
Author-email: Elliot Simpson <elliot@p-s.co.nz>
License-Expression: AGPL-3.0-or-later
License-File: LICENSE.txt
Keywords: generate,pelican,static,website
Classifier: Development Status :: 2 - Pre-Alpha
Classifier: Environment :: Console
Classifier: Framework :: Pelican
Classifier: Intended Audience :: Developers
Classifier: License :: OSI Approved :: GNU Affero General Public License v3 or later (AGPLv3+)
Classifier: Operating System :: OS Independent
Classifier: Programming Language :: Python
Classifier: Programming Language :: Python :: 3 :: Only
Classifier: Programming Language :: Python :: 3.11
Classifier: Programming Language :: Python :: 3.12
Classifier: Programming Language :: Python :: 3.13
Classifier: Topic :: Internet :: WWW/HTTP :: Site Management
Classifier: Topic :: Software Development :: Code Generators
Classifier: Topic :: Software Development :: Libraries :: Python Modules
Classifier: Typing :: Typed
Requires-Python: >=3.11
Requires-Dist: langcodes>=3.5.0
Requires-Dist: pydantic>=2.11.4
Requires-Dist: tomlkit>=0.13.3
Requires-Dist: tzdata>=2025.2
Requires-Dist: tzlocal>=5.3.1
